{
  "type": "feat",
  "name": "Adaptive Defense",
  "folder": null,
  "img": "modules/starfinder-field-test-for-pf2e/art/icons/feat.webp",
  "system": {
    "description": {
      "gm": "",
      "value": "<p><strong>Transfer Cost</strong> 2</p><hr /><p>You prepare your vitality network to catch some of your excess magic, allowing it to flow back and bolster your bond's defenses. If the next action you use is to Cast a Spell that deals damage, whether or not it successfully deals damage, you and your bonded allies gain resistance to that type of damage equal to the spell's rank (minimum 1) until the end of your next turn. If the spell deals more than one type of damage, choose one and gain resistance to that type.</p>"
    },
    "rules": [],
    "slug": "adaptive-defense",
    "_migration": {
      "version": 0.932,
      "lastMigration": null,
      "previous": {
        "schema": null,
        "foundry": "12.328",
        "system": "6.0.4"
      }
    },
    "traits": {
      "otherTags": [],
      "value": [
        "concentrate",
        "emotion",
        "manipulate",
        "mental",
        "mystic",
        "spellshape",
        "transfer"
      ],
      "rarity": "common"
    },
    "publication": {
      "title": "Starfinder Second Edition Playtest Rulebook",
      "authors": "",
      "license": "ORC",
      "remaster": true
    },
    "level": {
      "value": 4
    },
    "category": "class",
    "onlyLevel1": false,
    "maxTakable": 1,
    "actionType": {
      "value": "action"
    },
    "actions": {
      "value": 1
    },
    "prerequisites": {
      "value": []
    },
    "location": null
  },
  "_id": "FjQSPX066fOXKe0b",
  "effects": [],
  "flags": {},
  "_stats": {
    "compendiumSource": null,
    "duplicateSource": null,
    "coreVersion": "12.331",
    "systemId": "pf2e",
    "systemVersion": "6.4.1",
    "createdTime": 1721801567540,
    "modifiedTime": 1729383095313,
    "lastModifiedBy": "HfiqVTKP7yuQgALu"
  },
  "sort": 5800000,
  "ownership": {
    "default": 0,
    "CmdglLq38DpgHzdd": 3
  },
  "_key": "!items!FjQSPX066fOXKe0b"
}
