{
  "name": "Crowd Control",
  "type": "feat",
  "effects": [],
  "system": {
    "description": {
      "gm": "",
      "value": "<p>You are experienced with influencing crowds. You gain a +2 circumstance bonus to Diplomacy on checks against crowds. The first time each round you Stride into a square containing a crowd, you can attempt a @Check[type:diplomacy|dc:20] check to try to move the crowd out of your way. A GM may use a different DC under certain circumstances, such as when the crowd has a level or set DC to disperse.</p>\n<hr />\n<p><strong>Critical Success</strong> As success, and the crowd departs from all adjacent squares as you move.</p>\n<p><strong>Success</strong> The crowd disperses from squares you move into.</p>\n<p><strong>Failure</strong> The crowd doesn't move, but you can continue moving.</p>\n<p><strong>Critical Failure</strong> The crowd forcefully resists you and disrupts your Stride.</p>"
    },
    "rules": [
      {
        "key": "FlatModifier",
        "selector": "diplomacy",
        "value": 2,
        "predicate": [
          "target:trait:crowd"
        ],
        "type": "circumstance"
      }
    ],
    "slug": "crowd-control",
    "_migration": {
      "version": 0.94,
      "previous": {
        "schema": 0.932,
        "foundry": "13.346",
        "system": "7.2.3"
      }
    },
    "traits": {
      "otherTags": [],
      "value": [
        "general",
        "skill"
      ],
      "rarity": "common"
    },
    "publication": {
      "title": "Starfinder Second Edition Playtest Rulebook",
      "authors": "",
      "license": "ORC",
      "remaster": true
    },
    "level": {
      "value": 2
    },
    "category": "skill",
    "onlyLevel1": false,
    "maxTakable": 1,
    "actionType": {
      "value": "passive"
    },
    "actions": {
      "value": null
    },
    "prerequisites": {
      "value": [
        {
          "value": "expert in Diplomacy"
        }
      ]
    },
    "location": null,
    "subfeatures": {
      "proficiencies": {},
      "senses": {},
      "suppressedFeatures": []
    }
  },
  "_id": "5wnkdovfDOVkxMlR",
  "img": "modules/starfinder-field-test-for-pf2e/art/icons/feat.webp",
  "folder": null,
  "sort": 30600000,
  "ownership": {
    "default": 0,
    "Wdx2rirHxbejveh1": 3
  },
  "flags": {},
  "_stats": {
    "systemId": "pf2e",
    "systemVersion": "7.2.3",
    "coreVersion": "13.346",
    "compendiumSource": null,
    "duplicateSource": null,
    "exportSource": null
  },
  "_key": "!items!5wnkdovfDOVkxMlR"
}
