{
  "name": "Electrical Shielding",
  "type": "feat",
  "effects": [],
  "system": {
    "description": {
      "gm": "",
      "value": "<p>Your body is insulated from electrical attacks. You gain electricity resistance equal to half your level (minimum 1). Additionally, you gain the @UUID[Compendium.starfinder-field-test-for-pf2e.actions.Item.ErXde8sIMDsCVPrJ]{Redirect Current} reaction.</p>"
    },
    "rules": [
      {
        "key": "Resistance",
        "type": "electricity",
        "value": "max(1,floor(@actor.level/2))"
      },
      {
        "key": "GrantItem",
        "uuid": "Compendium.starfinder-field-test-for-pf2e.actions.Item.ErXde8sIMDsCVPrJ"
      }
    ],
    "slug": "electrical-shielding",
    "_migration": {
      "version": 0.932,
      "lastMigration": null,
      "previous": {
        "schema": 0.917,
        "foundry": "12.328",
        "system": "6.1.1"
      }
    },
    "traits": {
      "otherTags": [],
      "value": [
        "prismeni"
      ],
      "rarity": "common"
    },
    "publication": {
      "title": "Starfinder Second Edition Playtest Rulebook",
      "authors": "",
      "license": "ORC",
      "remaster": true
    },
    "level": {
      "value": 5
    },
    "category": "ancestry",
    "onlyLevel1": false,
    "maxTakable": 1,
    "actionType": {
      "value": "passive"
    },
    "actions": {
      "value": null
    },
    "prerequisites": {
      "value": []
    },
    "location": null
  },
  "_id": "zX7SZ85OKyxEEaQy",
  "img": "modules/starfinder-field-test-for-pf2e/art/icons/feat.webp",
  "folder": null,
  "sort": 38300000,
  "ownership": {
    "default": 0,
    "jqoxBUkgpBQ7vlMR": 3
  },
  "flags": {},
  "_stats": {
    "systemId": "pf2e",
    "systemVersion": "6.1.2",
    "coreVersion": "12.330",
    "createdTime": 1708148281517,
    "modifiedTime": 1722286691605,
    "lastModifiedBy": "CmdglLq38DpgHzdd",
    "compendiumSource": null,
    "duplicateSource": null
  },
  "_key": "!items!zX7SZ85OKyxEEaQy"
}
