{
  "name": "Shroud of Shattered Spirits",
  "type": "feat",
  "effects": [],
  "system": {
    "description": {
      "gm": "",
      "value": "<p><strong>Frequency</strong> once per day</p><p><strong>Trigger</strong> An enemy's Strike or targeted effect would hit you and you weren't already @UUID[Compendium.pf2e.conditionitems.Item.DmAIPqOBomZ7H95W]{Concealed}, @UUID[Compendium.pf2e.conditionitems.Item.iU0fEDdBp3rXpTMC]{Hidden}, or @UUID[Compendium.pf2e.conditionitems.Item.VRSef5y1LmL2Hkjf]{Undetected} by that enemy.</p><hr /><p>Your mere presence attracts restless spirits, haunted objects, spiritually active substances and fragmented souls, like a magnet attracts iron. You manifest these spirit shards in a chaotic whirlwind around you that you barely control with your thoughts. You become concealed until the beginning of your next turn, and the flat check for concealment applies to the triggering Strike or effect that would have hit you. If the flat check fails, the Strike or effect misses you.</p>"
    },
    "rules": [],
    "slug": "shroud-of-shattered-spirits",
    "_migration": {
      "version": 0.932,
      "lastMigration": null,
      "previous": {
        "schema": 0.917,
        "foundry": "12.328",
        "system": "6.1.1"
      }
    },
    "traits": {
      "otherTags": [],
      "value": [
        "borai"
      ],
      "rarity": "common"
    },
    "publication": {
      "title": "Starfinder Second Edition Playtest Rulebook",
      "authors": "",
      "license": "ORC",
      "remaster": true
    },
    "level": {
      "value": 9
    },
    "category": "ancestry",
    "onlyLevel1": false,
    "maxTakable": 1,
    "actionType": {
      "value": "reaction"
    },
    "actions": {
      "value": null
    },
    "prerequisites": {
      "value": []
    },
    "location": null,
    "frequency": {
      "max": 1,
      "per": "day"
    }
  },
  "_id": "VoaUxllzmHG1uptJ",
  "img": "modules/starfinder-field-test-for-pf2e/art/icons/feat.webp",
  "folder": null,
  "sort": 35100000,
  "ownership": {
    "default": 0,
    "jqoxBUkgpBQ7vlMR": 3
  },
  "flags": {},
  "_stats": {
    "systemId": "pf2e",
    "systemVersion": "6.1.3",
    "coreVersion": "12.330",
    "compendiumSource": null,
    "duplicateSource": null
  },
  "_key": "!items!VoaUxllzmHG1uptJ"
}
