{
  "name": "Synthetic Speech",
  "type": "feat",
  "effects": [],
  "system": {
    "description": {
      "gm": "",
      "value": "<p>You can connect with computers. You can cast @UUID[Compendium.starfinder-field-test-for-pf2e.spells.Item.AuzNHVHvsQPFIOQT]{Speak with Computers} on yourself once per day as an innate arcane spell.</p>"
    },
    "rules": [],
    "slug": "synthetic-speech",
    "_migration": {
      "version": 0.94,
      "previous": {
        "schema": 0.932,
        "foundry": "13.346",
        "system": "7.2.3"
      }
    },
    "traits": {
      "otherTags": [],
      "value": [
        "android"
      ],
      "rarity": "common"
    },
    "publication": {
      "title": "Starfinder Second Edition Playtest Rulebook",
      "authors": "",
      "license": "ORC",
      "remaster": true
    },
    "level": {
      "value": 13
    },
    "category": "ancestry",
    "onlyLevel1": false,
    "maxTakable": 1,
    "actionType": {
      "value": "passive"
    },
    "actions": {
      "value": null
    },
    "prerequisites": {
      "value": [
        {
          "value": "artificial scion or networked heritage"
        }
      ]
    },
    "location": null,
    "subfeatures": {
      "proficiencies": {},
      "senses": {},
      "suppressedFeatures": []
    }
  },
  "img": "modules/starfinder-field-test-for-pf2e/art/icons/feat.webp",
  "folder": null,
  "ownership": {
    "default": 0,
    "osGt3Y9EUYsTtPet": 3
  },
  "flags": {
    "core": {}
  },
  "_stats": {
    "systemId": "pf2e",
    "systemVersion": "7.2.3",
    "coreVersion": "13.346",
    "compendiumSource": null,
    "duplicateSource": null,
    "exportSource": null
  },
  "_id": "tdFkksuGVAEQC37b",
  "sort": 47800000,
  "_key": "!items!tdFkksuGVAEQC37b"
}
