{
  "folder": null,
  "name": "Oras",
  "type": "deity",
  "effects": [],
  "system": {
    "description": {
      "gm": "",
      "value": "<h2>Agent of Change</h2><p>Oras is a god of transformation through science who evolved from a single-celled organism into a deity. He teaches others to unlock their true potential by surpassing their genetic code and augmenting their bodies.</p><p><strong>Areas of Concern</strong> adaptation, evolution, and natural selection</p><p><strong>Edicts</strong> adapt to new situations, evolve, embrace change</p><p><strong>Anathema</strong> fear change, stagnate into complacency, prevent others from changing into their desired forms</p>"
    },
    "rules": [],
    "slug": "oras",
    "_migration": {
      "version": 0.932,
      "lastMigration": null
    },
    "traits": {
      "otherTags": []
    },
    "publication": {
      "title": "Starfinder Second Edition Playtest Rulebook",
      "authors": "",
      "license": "ORC",
      "remaster": true
    },
    "category": "deity",
    "sanctification": {
      "modal": "can",
      "what": [
        "holy",
        "unholy"
      ]
    },
    "domains": {
      "primary": [
        "change",
        "healing",
        "nature",
        "repose"
      ],
      "alternate": []
    },
    "font": [
      "harm",
      "heal"
    ],
    "attribute": [
      "con",
      "str"
    ],
    "skill": [
      "nature"
    ],
    "weapons": [
      "injection-rifle"
    ],
    "spells": {
      "1": "Compendium.starfinder-field-test-for-pf2e.spells.Item.gUNeahoAJMH9Uatm",
      "4": "Compendium.starfinder-field-test-for-pf2e.spells.Item.dL4azBx0aql8Mgfs",
      "9": "Compendium.pf2e.spells-srd.Item.pswdik31kuHEvdno"
    }
  },
  "img": "modules/starfinder-field-test-for-pf2e/art/deities/oras.webp",
  "flags": {},
  "_stats": {
    "compendiumSource": null,
    "duplicateSource": null,
    "coreVersion": "12.330",
    "systemId": "pf2e",
    "systemVersion": "6.1.3"
  },
  "_id": "dGEgnEZyhj5HJqVa",
  "sort": 0,
  "ownership": {
    "default": 0,
    "CmdglLq38DpgHzdd": 3
  },
  "_key": "!items!dGEgnEZyhj5HJqVa"
}
