{
  "folder": null,
  "name": "Motivating Ringtone",
  "type": "spell",
  "effects": [],
  "system": {
    "description": {
      "gm": "",
      "value": "<p>You cause the target comm unit to play a cosmically composed personal theme song specific to its owner. The creature who owns the target regains 1d8+4 Hit Points when you Cast the Spell and a +5-foot status bonus to all Speeds and a +1 status bonus to saves against fear effects for the duration, as long as the comm unit continues to play the ringtone. Creatures beginning their turn adjacent to an ally with an active ringtone gain the status bonus to Speeds and bonus to saves until the start of their next turn.</p><p>@UUID[Compendium.starfinder-field-test-for-pf2e.conditions.Item.HshG8G3NgMJNlu9s]{Spell Effect: Motivating Ringtone}</p><hr /><p><strong>Heightened (+1)</strong> The amount of healing increases by 1d8+4.</p>"
    },
    "rules": [],
    "slug": "motivating-ringtone",
    "_migration": {
      "version": 0.94,
      "lastMigration": null,
      "previous": {
        "schema": 0.932,
        "foundry": "13.346",
        "system": "7.2.3"
      }
    },
    "traits": {
      "otherTags": [],
      "value": [
        "auditory",
        "concentrate",
        "emotion",
        "healing",
        "manipulate",
        "subtle"
      ],
      "rarity": "common",
      "traditions": [
        "divine",
        "occult"
      ]
    },
    "publication": {
      "title": "Starfinder Second Edition Playtest Rulebook",
      "authors": "",
      "license": "ORC",
      "remaster": true
    },
    "level": {
      "value": 1
    },
    "requirements": "you have a comm unit, used as a locus, and the phone number of the target",
    "target": {
      "value": "1 comm unit"
    },
    "range": {
      "value": "120 feet"
    },
    "area": null,
    "time": {
      "value": "2"
    },
    "duration": {
      "value": "1 minute",
      "sustained": false
    },
    "damage": {
      "zaLYHFhRkUPLsOES": {
        "formula": "1d8+4",
        "kinds": [
          "healing"
        ],
        "type": "untyped",
        "category": null,
        "materials": [],
        "applyMod": false
      }
    },
    "defense": null,
    "cost": {
      "value": ""
    },
    "location": {
      "value": ""
    },
    "counteraction": false,
    "heightening": {
      "type": "interval",
      "interval": 1,
      "damage": {
        "zaLYHFhRkUPLsOES": "1d8+4"
      }
    }
  },
  "img": "icons/magic/sonic/projectile-sound-rings-wave.webp",
  "flags": {},
  "_stats": {
    "systemId": "pf2e",
    "systemVersion": "7.2.3",
    "coreVersion": "13.346",
    "compendiumSource": null,
    "duplicateSource": null,
    "exportSource": null
  },
  "_id": "jCr8Airvs1u5D1yR",
  "sort": 8900000,
  "ownership": {
    "default": 0,
    "qA45GVv5hySaf9b5": 3
  },
  "_key": "!items!jCr8Airvs1u5D1yR"
}
