{
  "img": "modules/starfinder-field-test-for-pf2e/art/icons/equipment/armor/armor%20blue%20medium.webp",
  "name": "Medium Armor Expertise",
  "system": {
    "actionType": {
      "value": "passive"
    },
    "actions": {
      "value": null
    },
    "category": "classfeature",
    "description": {
      "value": "<p>You've learned to defend yourself better against attacks. Your proficiency ranks for light armor, medium armor, and unarmored defense increase to expert.</p>",
      "gm": ""
    },
    "level": {
      "value": 11
    },
    "prerequisites": {
      "value": []
    },
    "publication": {
      "license": "ORC",
      "remaster": true,
      "title": "Starfinder Tech Class Playtest",
      "authors": ""
    },
    "rules": [],
    "subfeatures": {
      "proficiencies": {
        "light": {
          "rank": 2,
          "attribute": null
        },
        "medium": {
          "rank": 2,
          "attribute": null
        },
        "unarmored": {
          "rank": 2,
          "attribute": null
        }
      },
      "senses": {},
      "suppressedFeatures": []
    },
    "traits": {
      "rarity": "common",
      "value": [
        "mechanic"
      ],
      "otherTags": []
    },
    "slug": "medium-armor-expertise",
    "_migration": {
      "version": 0.935,
      "previous": null
    },
    "onlyLevel1": false,
    "maxTakable": 1,
    "location": null
  },
  "type": "feat",
  "_stats": {
    "compendiumSource": null,
    "duplicateSource": null,
    "coreVersion": "12.331",
    "systemId": "pf2e",
    "systemVersion": "6.11.1",
    "createdTime": 1745274410486,
    "modifiedTime": 1745274497865,
    "lastModifiedBy": "eUnac0oMbpEwem24"
  },
  "effects": [],
  "folder": "LhdfGVgPMQncD5yl",
  "ownership": {
    "default": 0,
    "eUnac0oMbpEwem24": 3
  },
  "flags": {},
  "_id": "pkwUUPwMaekiwIjH",
  "sort": 0,
  "_key": "!items!pkwUUPwMaekiwIjH"
}
